cnki2bibtex/__init__.py
cnki2bibtex/bibtex_entry.py
cnki2bibtex/cnki2bib.py
cnki2bibtex/cnki_entry.py
cnki2bibtex/entry.py
cnki2bibtex/misc/__init__.py
cnki2bibtex/misc/check.py
cnki2bibtex/misc/configure.py
cnki2bib-0.2.8.dist-info/LICENSE
cnki2bib-0.2.8.dist-info/METADATA
cnki2bib-0.2.8.dist-info/WHEEL
cnki2bib-0.2.8.dist-info/entry_points.txt
cnki2bib-0.2.8.dist-info/top_level.txt
cnki2bib-0.2.8.dist-info/RECORD
