Metadata-Version: 2.1
Name: cnki2bib
Version: 0.2.8
Summary: Converting the NoteExpress file (.net) exported by CNKI to BibTeX file (.bib)
Home-page: https://github.com/Vopaaz/CNKI_2_BibTeX
Author: Vopaaz
Author-email: liyifan945@gmail.com
License-File: LICENSE
Requires-Dist: Click
Requires-Dist: jieba
Requires-Dist: pyperclip
Requires-Dist: pypinyin
